{
  "groups": [
    {
      "form": {
        "radiusMin": 60,
        "radiusMax": 60,
        "size": 50
      },

      "elements": [
        {"file": "logo/LOGO-01.png"},
        {"file": "logo/LOGO-02.png"},
        {"file": "logo/LOGO-03.png"},
        {"file": "logo/LOGO-04.png"},
        {"file": "logo/LOGO-05.png"},
        {"file": "logo/LOGO-06.png"},
        {"file": "logo/LOGO-07.png"},
        {"file": "logo/LOGO-08.png"},
        {"file": "logo/LOGO-09.png"},
        {"file": "logo/LOGO-10.png"},
        {"file": "logo/LOGO-11.png"}
      ]
    },
    {
      "form": {
        "radiusMin": 180,
        "radiusMax": 180,
        "size": 150
      },

      "elements": [
        {"file": "22/SMART_TAGS-06.png"},
        {"file": "22/SMART_TAGS-07.png"},
        {"file": "22/SMART_TAGS-08.png"},
        {"file": "22/SMART_TAGS-09.png"},
        {"file": "22/SMART_TAGS-10.png"},
        {"file": "22/SMART_TAGS-11.png"},
        {"file": "22/SMART_TAGS-12.png"},
        {"file": "22/SMART_TAGS-13.png"},
        {"file": "22/SMART_TAGS-14.png"}
      ]
    },
    {
      "form": {
        "radiusMin": 320,
        "radiusMax": 320,
        "size": 300
      },

      "elements": [
        {"file": "3/3-01.png"},
        {"file": "3/3-02.png"},
        {"file": "3/3-03.png"},
        {"file": "3/3-04.png"},
        {"file": "3/3-05.png"}
      ]
    }
  ],
  "layers": [
    {"value": 100},
    {"value": 400},
    {"value": 700}
  ]
}